<nfeProc versao="3.10" xmlns="http://www.portalfiscal.inf.br/nfe"><NFe xmlns="http://www.portalfiscal.inf.br/nfe"><infNFe Id="NFe35170119917881000480550010000217331154181673" versao="3.10"><ide><cUF>35</cUF><cNF>15418167</cNF><natOp>Venda merc.adq.receb.de terceiros</natOp><indPag>1</indPag><mod>55</mod><serie>1</serie><nNF>21733</nNF><dhEmi>2017-01-09T13:07:29-02:00</dhEmi><dhSaiEnt>2017-01-09T15:09:59-02:00</dhSaiEnt><tpNF>1</tpNF><idDest>2</idDest><cMunFG>3518800</cMunFG><tpImp>1</tpImp><tpEmis>1</tpEmis><cDV>3</cDV><tpAmb>1</tpAmb><finNFe>1</finNFe><indFinal>0</indFinal><indPres>9</indPres><procEmi>0</procEmi><verProc>TrustFiles</verProc></ide><emit><CNPJ>19917881000480</CNPJ><xNome>THE CHEMOURS CO IND E COM P QUIM LT</xNome><enderEmit><xLgr>ESTRADA MUNICIPAL</xLgr><nro>1156</nro><xCpl>BL C; SL 1</xCpl><xBairro>JARDIM SANTO AFONSO</xBairro><cMun>3518800</cMun><xMun>GUARULHOS</xMun><UF>SP</UF><CEP>07215040</CEP><cPais>1058</cPais><xPais>Brasil</xPais><fone>0113478081</fone></enderEmit><IE>796238862112</IE><CRT>3</CRT></emit><dest><CNPJ>39118153000173</CNPJ><xNome>POLIPARTES COM REFR E AR COND LTDA ETRODOM LTDA</xNome><enderDest><xLgr>R DO RESENDE</xLgr><nro>95</nro><xCpl>LOJA A</xCpl><xBairro>CENTRO</xBairro><cMun>3304557</cMun><xMun>RIO DE JANEIRO</xMun><UF>RJ</UF><CEP>20231091</CEP><cPais>1058</cPais><xPais>Brasil</xPais><fone>2124611133</fone></enderDest><indIEDest>1</indIEDest><IE>85203606</IE><email>nfe@polipartes.com.br;simone.almeida@grupotoniato.com.br</email></dest><autXML><CNPJ>19917881000480</CNPJ></autXML><det nItem="1"><prod><cProd>D13359700</cProd><cEAN /><xProd>FREON 134A 11.25 KG BOX/15 0.750 KG VAL</xProd><NCM>29033911</NCM><EXTIPI>011</EXTIPI><CFOP>6102</CFOP><uCom>PCA</uCom><qCom>120.0000</qCom><vUnCom>17.5425000000</vUnCom><vProd>2105.10</vProd><cEANTrib /><uTrib>PCA</uTrib><qTrib>120.0000</qTrib><vUnTrib>17.5425000000</vUnTrib><indTot>1</indTot><xPed>DAVIDSON</xPed><nItemPed>000010</nItemPed></prod><imposto><ICMS><ICMS00><orig>6</orig><CST>00</CST><modBC>3</modBC><vBC>2105.10</vBC><pICMS>12.00</pICMS><vICMS>252.61</vICMS></ICMS00></ICMS><IPI><CNPJProd>19917881000480</CNPJProd><cEnq>999</cEnq><IPINT><CST>53</CST></IPINT></IPI><PIS><PISAliq><CST>01</CST><vBC>2105.10</vBC><pPIS>1.65</pPIS><vPIS>34.73</vPIS></PISAliq></PIS><COFINS><COFINSAliq><CST>01</CST><vBC>2105.10</vBC><pCOFINS>7.60</pCOFINS><vCOFINS>159.99</vCOFINS></COFINSAliq></COFINS></imposto></det><det nItem="2"><prod><cProd>D11666186</cProd><cEAN /><xProd>FREON 22 15 KG BOX/15 1KG CAN-VAL</xProd><NCM>29037100</NCM><EXTIPI>000</EXTIPI><CFOP>6102</CFOP><uCom>PCA</uCom><qCom>45.0000</qCom><vUnCom>43.4000000000</vUnCom><vProd>1953.00</vProd><cEANTrib /><uTrib>PCA</uTrib><qTrib>45.0000</qTrib><vUnTrib>43.4000000000</vUnTrib><indTot>1</indTot><xPed>DAVIDSON</xPed><nItemPed>000020</nItemPed></prod><imposto><ICMS><ICMS00><orig>1</orig><CST>00</CST><modBC>3</modBC><vBC>1953.00</vBC><pICMS>4.00</pICMS><vICMS>78.12</vICMS></ICMS00></ICMS><IPI><CNPJProd>19917881000480</CNPJProd><cEnq>999</cEnq><IPINT><CST>53</CST></IPINT></IPI><PIS><PISAliq><CST>01</CST><vBC>1953.00</vBC><pPIS>1.65</pPIS><vPIS>32.22</vPIS></PISAliq></PIS><COFINS><COFINSAliq><CST>01</CST><vBC>1953.00</vBC><pCOFINS>7.60</pCOFINS><vCOFINS>148.43</vCOFINS></COFINSAliq></COFINS></imposto></det><det nItem="3"><prod><cProd>D12837456</cProd><cEAN /><xProd>FREON 22 DAC C/ 13,62KG</xProd><NCM>29037100</NCM><EXTIPI>000</EXTIPI><CFOP>6102</CFOP><uCom>KG</uCom><qCom>340.5000</qCom><vUnCom>29.0700150000</vUnCom><vProd>9898.34</vProd><cEANTrib /><uTrib>KG</uTrib><qTrib>340.5000</qTrib><vUnTrib>29.0700150000</vUnTrib><indTot>1</indTot><xPed>DAVIDSON</xPed><nItemPed>000030</nItemPed></prod><imposto><ICMS><ICMS00><orig>1</orig><CST>00</CST><modBC>3</modBC><vBC>9898.34</vBC><pICMS>4.00</pICMS><vICMS>395.93</vICMS></ICMS00></ICMS><IPI><CNPJProd>19917881000480</CNPJProd><cEnq>999</cEnq><IPINT><CST>53</CST></IPINT></IPI><PIS><PISAliq><CST>01</CST><vBC>9898.34</vBC><pPIS>1.65</pPIS><vPIS>163.32</vPIS></PISAliq></PIS><COFINS><COFINSAliq><CST>01</CST><vBC>9898.34</vBC><pCOFINS>7.60</pCOFINS><vCOFINS>752.27</vCOFINS></COFINSAliq></COFINS></imposto></det><det nItem="4"><prod><cProd>D12837432</cProd><cEAN /><xProd>FREON TM  134a DAC C/ 13,62KG</xProd><NCM>29033911</NCM><EXTIPI>011</EXTIPI><CFOP>6102</CFOP><uCom>KG</uCom><qCom>108.9600</qCom><vUnCom>20.5500180000</vUnCom><vProd>2239.13</vProd><cEANTrib /><uTrib>KG</uTrib><qTrib>108.9600</qTrib><vUnTrib>20.5500180000</vUnTrib><indTot>1</indTot><xPed>DAVIDSON</xPed><nItemPed>000050</nItemPed></prod><imposto><ICMS><ICMS00><orig>6</orig><CST>00</CST><modBC>3</modBC><vBC>2239.13</vBC><pICMS>12.00</pICMS><vICMS>268.70</vICMS></ICMS00></ICMS><IPI><CNPJProd>19917881000480</CNPJProd><cEnq>999</cEnq><IPINT><CST>53</CST></IPINT></IPI><PIS><PISAliq><CST>01</CST><vBC>2239.13</vBC><pPIS>1.65</pPIS><vPIS>36.95</vPIS></PISAliq></PIS><COFINS><COFINSAliq><CST>01</CST><vBC>2239.13</vBC><pCOFINS>7.60</pCOFINS><vCOFINS>170.17</vCOFINS></COFINSAliq></COFINS></imposto></det><det nItem="5"><prod><cProd>D15339791</cProd><cEAN /><xProd>FREON TM  410A 11.35KG/25LB DAC LA</xProd><NCM>38247890</NCM><EXTIPI>090</EXTIPI><CFOP>6102</CFOP><uCom>KG</uCom><qCom>56.7500</qCom><vUnCom>24.1800880000</vUnCom><vProd>1372.22</vProd><cEANTrib /><uTrib>KG</uTrib><qTrib>56.7500</qTrib><vUnTrib>24.1800880000</vUnTrib><indTot>1</indTot><xPed>DAVIDSON</xPed><nItemPed>000060</nItemPed></prod><imposto><ICMS><ICMS00><orig>1</orig><CST>00</CST><modBC>3</modBC><vBC>1372.22</vBC><pICMS>4.00</pICMS><vICMS>54.89</vICMS></ICMS00></ICMS><IPI><CNPJProd>19917881000480</CNPJProd><cEnq>999</cEnq><IPITrib><CST>50</CST><vBC>1372.22</vBC><pIPI>10.00</pIPI><vIPI>137.22</vIPI></IPITrib></IPI><PIS><PISAliq><CST>01</CST><vBC>1372.22</vBC><pPIS>1.65</pPIS><vPIS>22.64</vPIS></PISAliq></PIS><COFINS><COFINSAliq><CST>01</CST><vBC>1372.22</vBC><pCOFINS>7.60</pCOFINS><vCOFINS>104.29</vCOFINS></COFINSAliq></COFINS></imposto></det><det nItem="6"><prod><cProd>D12837393</cProd><cEAN /><xProd>FREON TM  404A 10.896KG/24LB DAC SRCEV</xProd><NCM>38247810</NCM><EXTIPI>010</EXTIPI><CFOP>6102</CFOP><uCom>KG</uCom><qCom>21.7920</qCom><vUnCom>25.8998720000</vUnCom><vProd>564.41</vProd><cEANTrib /><uTrib>KG</uTrib><qTrib>21.7920</qTrib><vUnTrib>25.8998720000</vUnTrib><indTot>1</indTot><xPed>DAVIDSON</xPed><nItemPed>000070</nItemPed></prod><imposto><ICMS><ICMS00><orig>6</orig><CST>00</CST><modBC>3</modBC><vBC>564.41</vBC><pICMS>12.00</pICMS><vICMS>67.73</vICMS></ICMS00></ICMS><IPI><CNPJProd>19917881000480</CNPJProd><cEnq>999</cEnq><IPITrib><CST>50</CST><vBC>564.41</vBC><pIPI>10.00</pIPI><vIPI>56.44</vIPI></IPITrib></IPI><PIS><PISAliq><CST>01</CST><vBC>564.41</vBC><pPIS>1.65</pPIS><vPIS>9.31</vPIS></PISAliq></PIS><COFINS><COFINSAliq><CST>01</CST><vBC>564.41</vBC><pCOFINS>7.60</pCOFINS><vCOFINS>42.90</vCOFINS></COFINSAliq></COFINS></imposto></det><total><ICMSTot><vBC>18132.20</vBC><vICMS>1117.98</vICMS><vICMSDeson>0.00</vICMSDeson><vBCST>0.00</vBCST><vST>0.00</vST><vProd>18132.20</vProd><vFrete>0.00</vFrete><vSeg>0.00</vSeg><vDesc>0.00</vDesc><vII>0.00</vII><vIPI>193.66</vIPI><vPIS>299.17</vPIS><vCOFINS>1378.05</vCOFINS><vOutro>0.00</vOutro><vNF>18325.86</vNF></ICMSTot></total><transp><modFrete>0</modFrete><transporta><CNPJ>29291184000682</CNPJ><xNome>TRANSPORTES TONIATO LTDA</xNome><IE>336151553115</IE><xEnder>EST MUNICIPAL GALPAOB 1156</xEnder><xMun>GUARULHOS</xMun><UF>SP</UF></transporta><vol><qVol>11</qVol><esp>CAIXAS</esp><pesoL>135.000</pesoL><pesoB>161.820</pesoB></vol><vol><qVol>40</qVol><esp>UNIDADES</esp><pesoL>528.002</pesoL><pesoB>646.044</pesoB></vol></transp><cobr><fat><nFat>7620781108</nFat><vOrig>18325.86</vOrig><vLiq>18325.86</vLiq></fat><dup><nDup>000021733/001</nDup><dVenc>2017-02-13</dVenc><vDup>6108.74</vDup></dup><dup><nDup>000021733/002</nDup><dVenc>2017-02-27</dVenc><vDup>6108.56</vDup></dup><dup><nDup>000021733/003</nDup><dVenc>2017-03-13</dVenc><vDup>6108.56</vDup></dup></cobr><infAdic><infCpl>Incidencia de COFINS, conf artigo 1  da Lei 10.833/03.||Op. trib. c/ Aliquota Basica||Incidencia de PIS, conforme artigo 1  da Lei 10.637/02.||Codigo IBAMA:621679.||Produto Perigoso, conf.Art.22,item 2,DL 96044/88,certificamo s que os||produtos estao adequadamente embalados ou acondicio nados para suportar||riscos de carregamento, transporte e des carregamento e transbordo.||Pedido:8500296859\\||Ped.Compra:DAVIDSON\\||Num.Entrega:6315560763\\</infCpl></infAdic><compra><xPed>DAVIDSON</xPed></compra></infNFe><Signature xmlns="http://www.w3.org/2000/09/xmldsig#"><SignedInfo><CanonicalizationMethod Algorithm="http://www.w3.org/TR/2001/REC-xml-c14n-20010315" /><SignatureMethod Algorithm="http://www.w3.org/2000/09/xmldsig#rsa-sha1" /><Reference URI="#NFe35170119917881000480550010000217331154181673"><Transforms><Transform Algorithm="http://www.w3.org/2000/09/xmldsig#enveloped-signature" /><Transform Algorithm="http://www.w3.org/TR/2001/REC-xml-c14n-20010315" /></Transforms><DigestMethod Algorithm="http://www.w3.org/2000/09/xmldsig#sha1" /><DigestValue>OwePZFNgoRRKv8WdPei1HFsDnGQ=</DigestValue></Reference></SignedInfo><SignatureValue>LCvD4UWnzg986XFOYliB648I64nuz+xqkJJeW3iOe+oyUyeHjuMVdSDaiWB+aQTKzRjW79KF1TN7
KU5nhGWQSB0b3c3q+UaIdTjwQar3QH9LHvyOL/FoSP2pUBUoUfVf/NdDgYDKc+AACG+SI29Zu4so
3kZP5geWO6Bh6o+/6aaUGg0+wKVpSnhRY0Z0TZuf6W+6MOeevVytgR5smVblnGspoHf3s+RRpOeJ
n6x5BoUUxioGyUjPmsZfQ4XJQ8j6C0fBiobb3zjKYoJ56qiNUPYwow+RGmuFBNBqfsQAtnIfl1o2
zLstwlshfIGjWhicyIlK7zmW7DBrsHysoPFPow==</SignatureValue><KeyInfo><X509Data><X509Certificate>MIIIiDCCBnCgAwIBAgIQWZcEw9q8uHf/F0CmOjnUvTANBgkqhkiG9w0BAQsFADB0MQswCQYDVQQG
EwJCUjETMBEGA1UEChMKSUNQLUJyYXNpbDEtMCsGA1UECxMkQ2VydGlzaWduIENlcnRpZmljYWRv
cmEgRGlnaXRhbCBTLkEuMSEwHwYDVQQDExhBQyBDZXJ0aXNpZ24gTXVsdGlwbGEgRzUwHhcNMTYw
NzI5MDAwMDAwWhcNMTcwNzI4MjM1OTU5WjCCAQoxCzAJBgNVBAYTAkJSMRMwEQYDVQQKFApJQ1At
QnJhc2lsMTYwNAYDVQQLFC1BdXRlbnRpY2FkbyBwb3IgQXV0b3JpZGFkZSBkZSBSZWdpc3RybyBD
TkIgU1AxGzAZBgNVBAsUEkFzc2luYXR1cmEgVGlwbyBBMTEWMBQGA1UECxQNSUQgLSAxMDc3MDk5
NzFJMEcGA1UEAxNAVEhFIENIRU1PVVJTIENPTVBBTlkgSU5EVVNUUklBIEUgQ09NRVJDSU8gREUg
UFJPRFVUT1MgUVVJTUlDT1MgTDEuMCwGCSqGSIb3DQEJARYfcGF0cmljaWEubS5ndWluYXRpQGNo
ZW1vdXJzLmNvbTCCASIwDQYJKoZIhvcNAQEBBQADggEPADCCAQoCggEBALYuV0eb0TSKIeX1EFa1
+yzLHS6QZ19iVNH9Ilnsbg/21Raa3e/Q6ASAE57W/bUuVrroPnwy2TuqHiBukI7qQh2bJIunCYxy
WM8+8RD4ga17trchn+JhR37ZHA9NfRpp/HJA+d50ZKwEMLj57N3p1nPvjK10PHmyi6E6754ohhcn
yDu1y9mPrgxfqRuAIRL9VhppcS5Ejz38ePduejM6RBgtdcAGF7n6A6GU73uzs+taVdSLwzn8d0rB
W/wY3WOyVA+ileVKdnJEUXhJUZ/nlaIXIqBNrD1+4mLJbA8IoyCPD8Wu7sHcczepkBZlbTExejbK
5Wff8dUFH+yf3+xSDAcCAwEAAaOCA3wwggN4MIHCBgNVHREEgbowgbegPQYFYEwBAwSgNAQyMDUw
NjE5ODAyNzUyNjA4Mjg0MDAwMDAwMDAwMDAwMDAwMDAwMzI5MzI5MTFYU1NQU1CgIQYFYEwBAwKg
GAQWUEFUUklDSUEgTU9VUkEgR1VJTkFUSaAZBgVgTAEDA6AQBA4xOTkxNzg4MTAwMDEzOKAXBgVg
TAEDB6AOBAwwMDAwMDAwMDAwMDCBH3BhdHJpY2lhLm0uZ3VpbmF0aUBjaGVtb3Vycy5jb20wCQYD
VR0TBAIwADAfBgNVHSMEGDAWgBSdUM+9/yTKr7Ez6xfiQnqOaSqOUzAOBgNVHQ8BAf8EBAMCBeAw
gYkGA1UdIASBgTB/MH0GBmBMAQIBCzBzMHEGCCsGAQUFBwIBFmVodHRwOi8vaWNwLWJyYXNpbC5j
ZXJ0aXNpZ24uY29tLmJyL3JlcG9zaXRvcmlvL2RwYy9BQ19DZXJ0aXNpZ25fTXVsdGlwbGEvRFBD
X0FDX0NlcnRpU2lnbk11bHRpcGxhLnBkZjCCASUGA1UdHwSCARwwggEYMFygWqBYhlZodHRwOi8v
aWNwLWJyYXNpbC5jZXJ0aXNpZ24uY29tLmJyL3JlcG9zaXRvcmlvL2xjci9BQ0NlcnRpc2lnbk11
bHRpcGxhRzUvTGF0ZXN0Q1JMLmNybDBboFmgV4ZVaHR0cDovL2ljcC1icmFzaWwub3V0cmFsY3Iu
Y29tLmJyL3JlcG9zaXRvcmlvL2xjci9BQ0NlcnRpc2lnbk11bHRpcGxhRzUvTGF0ZXN0Q1JMLmNy
bDBboFmgV4ZVaHR0cDovL3JlcG9zaXRvcmlvLmljcGJyYXNpbC5nb3YuYnIvbGNyL0NlcnRpc2ln
bi9BQ0NlcnRpc2lnbk11bHRpcGxhRzUvTGF0ZXN0Q1JMLmNybDAdBgNVHSUEFjAUBggrBgEFBQcD
AgYIKwYBBQUHAwQwgaAGCCsGAQUFBwEBBIGTMIGQMGQGCCsGAQUFBzAChlhodHRwOi8vaWNwLWJy
YXNpbC5jZXJ0aXNpZ24uY29tLmJyL3JlcG9zaXRvcmlvL2NlcnRpZmljYWRvcy9BQ19DZXJ0aXNp
Z25fTXVsdGlwbGFfRzUucDdjMCgGCCsGAQUFBzABhhxodHRwOi8vb2NzcC5jZXJ0aXNpZ24uY29t
LmJyMA0GCSqGSIb3DQEBCwUAA4ICAQBsX06T9uFN2i6OfRvy7Ii+iXOv8KZebNv+HytmaY17VPQJ
oB4zF8hzTMKTrUMm+ssKchnl9F5WvJOO35xksUE7xKYI7NP1VRsD0T50Imv4UvPaBjh+tnLtKnnU
vUwTN+KDdcPY/uAgVaUXJR+54Qiikpyi3F/MCipFmhYxDXe14ZoUUNftSdDQ/YDhSjNC3sZpjQJF
5eMWuIn4CTzbFMEwdEMg5U8KF1NKZoraKNQfNOThYeNFrfF82EOZt5sEY15zekA6Vj53vI+mOnzX
Sl93nKO2fkoCv5GLj4aiK6XkyeIMxgfJVGBtcMrXoaI7hZhoSHkgcWbTyHXspEuHHTbok+1M4jSb
FIc7nS3xGPvpx7eG6tfvTVutH4cYVCGtPjGcTsBzXALYVaD6gsJEIzVQwJSHmXqUECGxAC6nKgr6
y8nIBEa7Cf7rM5qJ7PCs6T5w2OxYvPdfN2gDiLNzuBrgPrzn8KO7pVlJHNhZG06IOzyZeLiKvVaf
kn5/PL06bqjZbA5qqUlPfhafEx6x3ktTrrkEKeSs15PmZdWdDqp6JpyY5atN22bRyP7jaWApMTu+
Om4f5o/KjhOpH5ndyK7cHUvjNA5BFD0grsbZIfbmCtUUI8ECPHKuw6v9IYfChZh+nzBXecGGclP1
ZIWW2/FZxPo82/kib8qEp+FccFZtfQ==</X509Certificate></X509Data></KeyInfo></Signature></NFe><protNFe versao="3.10"><infProt Id="Id135170014386690"><tpAmb>1</tpAmb><verAplic>SP_NFE_PL_008i2</verAplic><chNFe>35170119917881000480550010000217331154181673</chNFe><dhRecbto>2017-01-09T13:11:08-02:00</dhRecbto><nProt>135170014386690</nProt><digVal>OwePZFNgoRRKv8WdPei1HFsDnGQ=</digVal><cStat>100</cStat><xMotivo>Autorizado o uso da NF-e</xMotivo></infProt></protNFe></nfeProc>
