<nfeProc versao="3.10" xmlns="http://www.portalfiscal.inf.br/nfe"><NFe xmlns="http://www.portalfiscal.inf.br/nfe"><infNFe versao="3.10" Id="NFe33170117467515003386550000004480071383084614"><ide><cUF>33</cUF><cNF>38308461</cNF><natOp>Vnd.mer.adq.rec.ter.mer.suj.sub.tri.con.con.sb. / Venda mer</natOp><indPag>1</indPag><mod>55</mod><serie>0</serie><nNF>448007</nNF><dhEmi>2017-01-23T12:35:44-02:00</dhEmi><dhSaiEnt>2017-01-24T05:00:00-02:00</dhSaiEnt><tpNF>1</tpNF><idDest>1</idDest><cMunFG>3304557</cMunFG><tpImp>2</tpImp><tpEmis>1</tpEmis><cDV>4</cDV><tpAmb>1</tpAmb><finNFe>1</finNFe><indFinal>0</indFinal><indPres>9</indPres><procEmi>0</procEmi><verProc>SAP GRC NFE 3.10</verProc></ide><emit><CNPJ>17467515003386</CNPJ><xNome>Cafe Tres Coracoes S.A</xNome><xFant>Tres Coracoes Prata</xFant><enderEmit><xLgr>ETR RIO DOURO</xLgr><nro>801</nro><xCpl>Bl2,GP 7a9</xCpl><xBairro>PARQUE COLUMBIA</xBairro><cMun>3304557</cMun><xMun>RIO DE JANEIRO</xMun><UF>RJ</UF><CEP>21535030</CEP><xPais>Brasil</xPais></enderEmit><IE>79216755</IE><CRT>3</CRT></emit><dest><CNPJ>11037284000107</CNPJ><xNome>BOMFRIOS COMERCIO DE ALIMENTOS LTDA</xNome><enderDest><xLgr>AV 22 DE MAIO LT 04 QDR 06</xLgr><nro>2856</nro><xBairro>LOTEAMENTO SANTO EXPEDITO</xBairro><cMun>3301900</cMun><xMun>ITABORAI</xMun><UF>RJ</UF><CEP>24885000</CEP><cPais>1058</cPais><xPais>Brasil</xPais><fone>2126351177</fone></enderDest><indIEDest>1</indIEDest><IE>78815655</IE></dest><det nItem="1"><prod><cProd>000000000012034044</cProd><cEAN>7896005802892</cEAN><xProd>Capp 3C Choc pt 200g 24</xProd><NCM>21011200</NCM><CFOP>5405</CFOP><uCom>CX</uCom><qCom>1.0000</qCom><vUnCom>140.4000000000</vUnCom><vProd>140.40</vProd><cEANTrib>7896005802892</cEANTrib><uTrib>UN</uTrib><qTrib>24.0000</qTrib><vUnTrib>5.8500000000</vUnTrib><indTot>1</indTot><xPed>201701190946548</xPed><nItemPed>000020</nItemPed></prod><imposto><ICMS><ICMS60><orig>0</orig><CST>60</CST><vBCSTRet>101.03</vBCSTRet><vICMSSTRet>13.21</vICMSSTRet></ICMS60></ICMS><IPI><cEnq>999</cEnq><IPINT><CST>53</CST></IPINT></IPI><PIS><PISNT><CST>06</CST></PISNT></PIS><COFINS><COFINSNT><CST>06</CST></COFINSNT></COFINS></imposto><infAdProd>BCST: 101.03 ICMSST REEMB: 13.21</infAdProd></det><det nItem="2"><prod><cProd>000000000012037408</cProd><cEAN>7896005803714</cEAN><xProd>Filtro Papel 3C 102/30 Desag c/aba</xProd><NCM>48232099</NCM><CFOP>5405</CFOP><uCom>CX</uCom><qCom>10.0000</qCom><vUnCom>80.7800000000</vUnCom><vProd>807.80</vProd><cEANTrib>7896005803714</cEANTrib><uTrib>UN</uTrib><qTrib>400.0000</qTrib><vUnTrib>2.0195000000</vUnTrib><vDesc>80.78</vDesc><indTot>1</indTot><xPed>201701190946548</xPed><nItemPed>000030</nItemPed></prod><imposto><ICMS><ICMS60><orig>0</orig><CST>60</CST><vBCSTRet>509.35</vBCSTRet><vICMSSTRet>47.47</vICMSSTRet></ICMS60></ICMS><IPI><cEnq>999</cEnq><IPINT><CST>53</CST></IPINT></IPI><PIS><PISAliq><CST>01</CST><vBC>727.02</vBC><pPIS>1.6500</pPIS><vPIS>12.00</vPIS></PISAliq></PIS><COFINS><COFINSAliq><CST>01</CST><vBC>727.02</vBC><pCOFINS>7.6000</pCOFINS><vCOFINS>55.25</vCOFINS></COFINSAliq></COFINS></imposto><infAdProd>BCST: 509.35 ICMSST REEMB: 47.47</infAdProd></det><det nItem="3"><prod><cProd>000000000012041029</cProd><cEAN>37896081800035</cEAN><xProd>Cafe Pimp Trad Std 500g</xProd><NCM>09012100</NCM><CFOP>5102</CFOP><uCom>CX</uCom><qCom>1.0000</qCom><vUnCom>89.0000000000</vUnCom><vProd>89.00</vProd><cEANTrib>7896081800034</cEANTrib><uTrib>UN</uTrib><qTrib>10.0000</qTrib><vUnTrib>8.9000000000</vUnTrib><vDesc>3.00</vDesc><indTot>1</indTot><xPed>201701190946548</xPed><nItemPed>000150</nItemPed></prod><imposto><ICMS><ICMS20><orig>0</orig><CST>20</CST><modBC>3</modBC><pRedBC>61.1100</pRedBC><vBC>33.45</vBC><pICMS>18.0000</pICMS><vICMS>6.02</vICMS></ICMS20></ICMS><IPI><cEnq>999</cEnq><IPINT><CST>53</CST></IPINT></IPI><PIS><PISNT><CST>06</CST></PISNT></PIS><COFINS><COFINSNT><CST>06</CST></COFINSNT></COFINS></imposto><infAdProd>Isento ou nao Sujeito a IPI. Cesta Basica -Dec.32.161/02 NF Emitida Termos Res SEF No 2.912/98</infAdProd></det><det nItem="4"><prod><cProd>000000000012047409</cProd><cEAN>7896081805114</cEAN><xProd>Filtro Papel Pimp 103/30 Desag c/aba</xProd><NCM>48232099</NCM><CFOP>5405</CFOP><uCom>CX</uCom><qCom>10.0000</qCom><vUnCom>89.2000000000</vUnCom><vProd>892.00</vProd><cEANTrib>7896081805114</cEANTrib><uTrib>UN</uTrib><qTrib>400.0000</qTrib><vUnTrib>2.2300000000</vUnTrib><vDesc>89.20</vDesc><indTot>1</indTot><xPed>201701190946548</xPed><nItemPed>000040</nItemPed></prod><imposto><ICMS><ICMS60><orig>0</orig><CST>60</CST><vBCSTRet>636.68</vBCSTRet><vICMSSTRet>59.34</vICMSSTRet></ICMS60></ICMS><IPI><cEnq>999</cEnq><IPINT><CST>53</CST></IPINT></IPI><PIS><PISAliq><CST>01</CST><vBC>802.80</vBC><pPIS>1.6500</pPIS><vPIS>13.25</vPIS></PISAliq></PIS><COFINS><COFINSAliq><CST>01</CST><vBC>802.80</vBC><pCOFINS>7.6000</pCOFINS><vCOFINS>61.01</vCOFINS></COFINSAliq></COFINS></imposto><infAdProd>BCST: 636.68 ICMSST REEMB: 59.34</infAdProd></det><det nItem="5"><prod><cProd>000000000012068123</cProd><cEAN>7896490290877</cEAN><xProd>Frisco Novo Salada de Fruta 8X15X25g</xProd><NCM>21069010</NCM><CFOP>5102</CFOP><uCom>UN</uCom><qCom>8.0000</qCom><vUnCom>9.0000000000</vUnCom><vProd>72.00</vProd><cEANTrib>7896490290716</cEANTrib><uTrib>SCH</uTrib><qTrib>120.0000</qTrib><vUnTrib>0.6000000000</vUnTrib><indTot>1</indTot><xPed>201701190946548</xPed><nItemPed>000120</nItemPed><nFCI>95C8B9A9-8C96-4D74-A427-074294992EA5</nFCI></prod><imposto><ICMS><ICMS00><orig>5</orig><CST>00</CST><modBC>3</modBC><vBC>72.00</vBC><pICMS>20.0000</pICMS><vICMS>14.40</vICMS></ICMS00></ICMS><IPI><cEnq>999</cEnq><IPINT><CST>53</CST></IPINT></IPI><PIS><PISAliq><CST>01</CST><vBC>72.00</vBC><pPIS>1.6500</pPIS><vPIS>1.19</vPIS></PISAliq></PIS><COFINS><COFINSAliq><CST>01</CST><vBC>72.00</vBC><pCOFINS>7.6000</pCOFINS><vCOFINS>5.47</vCOFINS></COFINSAliq></COFINS></imposto><infAdProd>Isento ou nao Sujeito a IPI.</infAdProd></det><det nItem="6"><prod><cProd>000000000012068124</cProd><cEAN>7896490290808</cEAN><xProd>Frisco Novo Laranja 8X15X25g</xProd><NCM>21069010</NCM><CFOP>5102</CFOP><uCom>UN</uCom><qCom>16.0000</qCom><vUnCom>9.0000000000</vUnCom><vProd>144.00</vProd><cEANTrib>7896490290648</cEANTrib><uTrib>SCH</uTrib><qTrib>240.0000</qTrib><vUnTrib>0.6000000000</vUnTrib><indTot>1</indTot><xPed>201701190946548</xPed><nItemPed>000060</nItemPed><nFCI>F0D1A8BD-B68F-412E-892D-1FE68DDAB141</nFCI></prod><imposto><ICMS><ICMS00><orig>5</orig><CST>00</CST><modBC>3</modBC><vBC>144.00</vBC><pICMS>20.0000</pICMS><vICMS>28.80</vICMS></ICMS00></ICMS><IPI><cEnq>999</cEnq><IPINT><CST>53</CST></IPINT></IPI><PIS><PISAliq><CST>01</CST><vBC>144.00</vBC><pPIS>1.6500</pPIS><vPIS>2.38</vPIS></PISAliq></PIS><COFINS><COFINSAliq><CST>01</CST><vBC>144.00</vBC><pCOFINS>7.6000</pCOFINS><vCOFINS>10.95</vCOFINS></COFINSAliq></COFINS></imposto><infAdProd>Isento ou nao Sujeito a IPI.</infAdProd></det><det nItem="7"><prod><cProd>000000000012068125</cProd><cEAN>7896490290891</cEAN><xProd>Frisco Novo Uva 8X15X25g</xProd><NCM>21069010</NCM><CFOP>5102</CFOP><uCom>UN</uCom><qCom>24.0000</qCom><vUnCom>9.0000000000</vUnCom><vProd>216.00</vProd><cEANTrib>7896490290730</cEANTrib><uTrib>SCH</uTrib><qTrib>360.0000</qTrib><vUnTrib>0.6000000000</vUnTrib><indTot>1</indTot><xPed>201701190946548</xPed><nItemPed>000110</nItemPed><nFCI>61C05BA5-85B3-4E20-B971-554443FF292C</nFCI></prod><imposto><ICMS><ICMS00><orig>5</orig><CST>00</CST><modBC>3</modBC><vBC>216.00</vBC><pICMS>20.0000</pICMS><vICMS>43.20</vICMS></ICMS00></ICMS><IPI><cEnq>999</cEnq><IPINT><CST>53</CST></IPINT></IPI><PIS><PISAliq><CST>01</CST><vBC>216.00</vBC><pPIS>1.6500</pPIS><vPIS>3.56</vPIS></PISAliq></PIS><COFINS><COFINSAliq><CST>01</CST><vBC>216.00</vBC><pCOFINS>7.6000</pCOFINS><vCOFINS>16.42</vCOFINS></COFINSAliq></COFINS></imposto><infAdProd>Isento ou nao Sujeito a IPI.</infAdProd></det><det nItem="8"><prod><cProd>000000000012068126</cProd><cEAN>7896490290846</cEAN><xProd>Frisco Novo Maracuja 8X15X25g</xProd><NCM>21069010</NCM><CFOP>5102</CFOP><uCom>UN</uCom><qCom>24.0000</qCom><vUnCom>9.0000000000</vUnCom><vProd>216.00</vProd><cEANTrib>7896490290686</cEANTrib><uTrib>SCH</uTrib><qTrib>360.0000</qTrib><vUnTrib>0.6000000000</vUnTrib><indTot>1</indTot><xPed>201701190946548</xPed><nItemPed>000090</nItemPed><nFCI>70372834-54E0-4956-982E-C44479C5EB85</nFCI></prod><imposto><ICMS><ICMS00><orig>5</orig><CST>00</CST><modBC>3</modBC><vBC>216.00</vBC><pICMS>20.0000</pICMS><vICMS>43.20</vICMS></ICMS00></ICMS><IPI><cEnq>999</cEnq><IPINT><CST>53</CST></IPINT></IPI><PIS><PISAliq><CST>01</CST><vBC>216.00</vBC><pPIS>1.6500</pPIS><vPIS>3.56</vPIS></PISAliq></PIS><COFINS><COFINSAliq><CST>01</CST><vBC>216.00</vBC><pCOFINS>7.6000</pCOFINS><vCOFINS>16.42</vCOFINS></COFINSAliq></COFINS></imposto><infAdProd>Isento ou nao Sujeito a IPI.</infAdProd></det><det nItem="9"><prod><cProd>000000000012068127</cProd><cEAN>7896490290747</cEAN><xProd>Frisco Novo Abacaxi 8X15X25g</xProd><NCM>21069010</NCM><CFOP>5102</CFOP><uCom>UN</uCom><qCom>8.0000</qCom><vUnCom>9.0000000000</vUnCom><vProd>72.00</vProd><cEANTrib>7896490290587</cEANTrib><uTrib>SCH</uTrib><qTrib>120.0000</qTrib><vUnTrib>0.6000000000</vUnTrib><indTot>1</indTot><xPed>201701190946548</xPed><nItemPed>000050</nItemPed><nFCI>E549DE51-E0E5-4FEB-BA2F-EA233E704064</nFCI></prod><imposto><ICMS><ICMS00><orig>5</orig><CST>00</CST><modBC>3</modBC><vBC>72.00</vBC><pICMS>20.0000</pICMS><vICMS>14.40</vICMS></ICMS00></ICMS><IPI><cEnq>999</cEnq><IPINT><CST>53</CST></IPINT></IPI><PIS><PISAliq><CST>01</CST><vBC>72.00</vBC><pPIS>1.6500</pPIS><vPIS>1.19</vPIS></PISAliq></PIS><COFINS><COFINSAliq><CST>01</CST><vBC>72.00</vBC><pCOFINS>7.6000</pCOFINS><vCOFINS>5.47</vCOFINS></COFINSAliq></COFINS></imposto><infAdProd>Isento ou nao Sujeito a IPI.</infAdProd></det><det nItem="10"><prod><cProd>000000000012068128</cProd><cEAN>7896490290839</cEAN><xProd>Frisco Novo Manga 8X15X25g</xProd><NCM>21069010</NCM><CFOP>5102</CFOP><uCom>UN</uCom><qCom>16.0000</qCom><vUnCom>9.0000000000</vUnCom><vProd>144.00</vProd><cEANTrib>7896490290679</cEANTrib><uTrib>SCH</uTrib><qTrib>240.0000</qTrib><vUnTrib>0.6000000000</vUnTrib><indTot>1</indTot><xPed>201701190946548</xPed><nItemPed>000080</nItemPed><nFCI>3E2B523C-4519-4009-AB38-6F3943297252</nFCI></prod><imposto><ICMS><ICMS00><orig>5</orig><CST>00</CST><modBC>3</modBC><vBC>144.00</vBC><pICMS>20.0000</pICMS><vICMS>28.80</vICMS></ICMS00></ICMS><IPI><cEnq>999</cEnq><IPINT><CST>53</CST></IPINT></IPI><PIS><PISAliq><CST>01</CST><vBC>144.00</vBC><pPIS>1.6500</pPIS><vPIS>2.38</vPIS></PISAliq></PIS><COFINS><COFINSAliq><CST>01</CST><vBC>144.00</vBC><pCOFINS>7.6000</pCOFINS><vCOFINS>10.94</vCOFINS></COFINSAliq></COFINS></imposto><infAdProd>Isento ou nao Sujeito a IPI.</infAdProd></det><det nItem="11"><prod><cProd>000000000012068129</cProd><cEAN>7896490290822</cEAN><xProd>Frisco Novo Limao 8X15X25g</xProd><NCM>21069010</NCM><CFOP>5102</CFOP><uCom>UN</uCom><qCom>16.0000</qCom><vUnCom>9.0000000000</vUnCom><vProd>144.00</vProd><cEANTrib>7896490290662</cEANTrib><uTrib>SCH</uTrib><qTrib>240.0000</qTrib><vUnTrib>0.6000000000</vUnTrib><indTot>1</indTot><xPed>201701190946548</xPed><nItemPed>000070</nItemPed><nFCI>39B9E2FD-4963-4E37-8DD3-70D177B07301</nFCI></prod><imposto><ICMS><ICMS00><orig>5</orig><CST>00</CST><modBC>3</modBC><vBC>144.00</vBC><pICMS>20.0000</pICMS><vICMS>28.80</vICMS></ICMS00></ICMS><IPI><cEnq>999</cEnq><IPINT><CST>53</CST></IPINT></IPI><PIS><PISAliq><CST>01</CST><vBC>144.00</vBC><pPIS>1.6500</pPIS><vPIS>2.38</vPIS></PISAliq></PIS><COFINS><COFINSAliq><CST>01</CST><vBC>144.00</vBC><pCOFINS>7.6000</pCOFINS><vCOFINS>10.94</vCOFINS></COFINSAliq></COFINS></imposto><infAdProd>Isento ou nao Sujeito a IPI.</infAdProd></det><det nItem="12"><prod><cProd>000000000012068131</cProd><cEAN>7896490290884</cEAN><xProd>Frisco Novo Tangerina 8X15X25g</xProd><NCM>21069010</NCM><CFOP>5102</CFOP><uCom>UN</uCom><qCom>8.0000</qCom><vUnCom>9.0000000000</vUnCom><vProd>72.00</vProd><cEANTrib>7896490290723</cEANTrib><uTrib>SCH</uTrib><qTrib>120.0000</qTrib><vUnTrib>0.6000000000</vUnTrib><indTot>1</indTot><xPed>201701190946548</xPed><nItemPed>000100</nItemPed><nFCI>35E4AD30-2F4A-4DD7-8F5A-1A60B01C2D18</nFCI></prod><imposto><ICMS><ICMS00><orig>5</orig><CST>00</CST><modBC>3</modBC><vBC>72.00</vBC><pICMS>20.0000</pICMS><vICMS>14.40</vICMS></ICMS00></ICMS><IPI><cEnq>999</cEnq><IPINT><CST>53</CST></IPINT></IPI><PIS><PISAliq><CST>01</CST><vBC>72.00</vBC><pPIS>1.6500</pPIS><vPIS>1.19</vPIS></PISAliq></PIS><COFINS><COFINSAliq><CST>01</CST><vBC>72.00</vBC><pCOFINS>7.6000</pCOFINS><vCOFINS>5.47</vCOFINS></COFINSAliq></COFINS></imposto><infAdProd>Isento ou nao Sujeito a IPI.</infAdProd></det><det nItem="13"><prod><cProd>000000000020038843</cProd><cEAN>17896005805104</cEAN><xProd>Capsula Tres Cafe Coado Classico 10X7,5</xProd><NCM>09012100</NCM><CFOP>5102</CFOP><uCom>CX</uCom><qCom>1.0000</qCom><vUnCom>95.8900000000</vUnCom><vProd>95.89</vProd><cEANTrib>7896005805107</cEANTrib><uTrib>CT</uTrib><qTrib>8.0000</qTrib><vUnTrib>11.9862500000</vUnTrib><indTot>1</indTot><xPed>201701190946548</xPed><nItemPed>000130</nItemPed></prod><imposto><ICMS><ICMS20><orig>2</orig><CST>20</CST><modBC>3</modBC><pRedBC>61.1100</pRedBC><vBC>37.29</vBC><pICMS>18.0000</pICMS><vICMS>6.71</vICMS></ICMS20></ICMS><IPI><cEnq>999</cEnq><IPINT><CST>53</CST></IPINT></IPI><PIS><PISNT><CST>06</CST></PISNT></PIS><COFINS><COFINSNT><CST>06</CST></COFINSNT></COFINS></imposto><infAdProd>Isento ou nao Sujeito a IPI. Cesta Basica -Dec.32.161/02 NF Emitida Termos Res SEF No 2.912/98</infAdProd></det><total><ICMSTot><vBC>1150.74</vBC><vICMS>228.73</vICMS><vICMSDeson>0.00</vICMSDeson><vBCST>0.00</vBCST><vST>0.00</vST><vProd>3105.09</vProd><vFrete>0.00</vFrete><vSeg>0.00</vSeg><vDesc>172.98</vDesc><vII>0.00</vII><vIPI>0.00</vIPI><vPIS>43.08</vPIS><vCOFINS>198.34</vCOFINS><vOutro>0.00</vOutro><vNF>2932.11</vNF></ICMSTot></total><transp><modFrete>0</modFrete><transporta><CNPJ>17467515003386</CNPJ><xNome>CAFE TRES CORACOES S.A</xNome><IE>79216755</IE><xEnder>EST RIO D'OURO 801, BL 2 G 7</xEnder><xMun>RIO DE JANEIRO</xMun><UF>RJ</UF></transporta><vol><qVol>143</qVol><nVol>129.403</nVol><pesoL>100.160</pesoL><pesoB>129.403</pesoB></vol></transp><cobr><dup><nDup>448007/01</nDup><dVenc>2017-02-27</dVenc><vDup>2932.11</vDup></dup></cobr><infAdic><infCpl>ICMS pago por sub tributaria, Decreto 45.612/2016 - RICMS-RJ - Isento ou nao Sujeito a IPI. - Filtro/Porta Filtro - ICMS ja cobrado por Substituicao Tributaria. - Conforme Decreto No 43.749/2012 RICMS/RJ. - Cesta Basica -Dec.32.161/02 NF Emitida Termos Res SEF No 2.912/98 - Num. Pedido: 201701190946548000441 - Cliente: 0002154996 BOM FRIOS</infCpl></infAdic></infNFe><Signature xmlns="http://www.w3.org/2000/09/xmldsig#"><SignedInfo><CanonicalizationMethod Algorithm="http://www.w3.org/TR/2001/REC-xml-c14n-20010315" /><SignatureMethod Algorithm="http://www.w3.org/2000/09/xmldsig#rsa-sha1" /><Reference URI="#NFe33170117467515003386550000004480071383084614"><Transforms><Transform Algorithm="http://www.w3.org/2000/09/xmldsig#enveloped-signature" /><Transform Algorithm="http://www.w3.org/TR/2001/REC-xml-c14n-20010315" /></Transforms><DigestMethod Algorithm="http://www.w3.org/2000/09/xmldsig#sha1" /><DigestValue>q1Q7R+aTObSsjY699QnzpskmsiI=</DigestValue></Reference></SignedInfo><SignatureValue>nGn52m7Txn6UOAqkOPZJdV6/xEd5k43rdGsMdnEqueCVrLpQeIiYvMNqrikwQYPA7X9Qz0/7osmZ
SFZsY7svTC/y+PBJ0B8AQkPNd/3fl2RcHOmFab/8RVCepI7FQvanG6I/Smb2NDetJvabtnuGtmBL
rEJug4PyZ0u6JNgsbk/1MsbIQIPVXHooveOg4iXOQ7EXby0aBi78tU7H7rIG4LMRCVLxEzXS7fZa
Hp4HkyjMMqmFTjmqK6Oyu/ouUJtPypw/9t7kKJqk1qX8UsK2UnZiQAm+YFsIbF4ZOPqfym3sEB0+
J2fesW4CgbcdUpC8JNrT05B2zGNZx1kJNajARQ==</SignatureValue><KeyInfo><X509Data><X509Certificate>MIIIWjCCBkKgAwIBAgIQB0vIjw0lKZsJwtRXkhXo/jANBgkqhkiG9w0BAQsFADB4MQswCQYDVQQG
EwJCUjETMBEGA1UEChMKSUNQLUJyYXNpbDE2MDQGA1UECxMtU2VjcmV0YXJpYSBkYSBSZWNlaXRh
IEZlZGVyYWwgZG8gQnJhc2lsIC0gUkZCMRwwGgYDVQQDExNBQyBDZXJ0aXNpZ24gUkZCIEc0MB4X
DTE2MDQxNDAwMDAwMFoXDTE3MDQxMzIzNTk1OVowgekxCzAJBgNVBAYTAkJSMRMwEQYDVQQKFApJ
Q1AtQnJhc2lsMQswCQYDVQQIEwJNRzEUMBIGA1UEBxQLU0FOVEEgTFVaSUExNjA0BgNVBAsULVNl
Y3JldGFyaWEgZGEgUmVjZWl0YSBGZWRlcmFsIGRvIEJyYXNpbCAtIFJGQjEWMBQGA1UECxQNUkZC
IGUtQ05QSiBBMTEiMCAGA1UECxQZQXV0ZW50aWNhZG8gcG9yIEFSIFNlcnZpcjEuMCwGA1UEAxMl
Q0FGRSBUUkVTIENPUkFDT0VTIFMgQToxNzQ2NzUxNTAwMDEwNzCCASIwDQYJKoZIhvcNAQEBBQAD
ggEPADCCAQoCggEBALGKvRx8JhmdvRohNr8Jo8CeTzK9vCGSobJYHuODl8nB5MjsO+luE8Rrnkds
p9a8sRHb8JHhODPMbsq1HvAZ6ZMHSKmV4fdsAWBD2FiAig3/xdYYjYRfct1MRPUuqBR8JDBAuj7I
uZ8BuwWVcb8zqEFMn+KT1suF5q6IJihzZzXoWGzrGu4mjDKDJIPZ2A1D0F+Qzfbv3tuKj7ZIzxjh
xrVI1OYKKC+h6V6d+5A4R0qI19F4wrEL2CwQw5DwPhD4SLha9zTaeSFve4EEj5PgIx2usl6Sos1n
iE5+xxuEx+6vUp82cBJ26vclaX4Ts/fRGmmhofTAW8wPosuijmJYs1sCAwEAAaOCA2wwggNoMIHR
BgNVHREEgckwgcagPQYFYEwBAwSgNAQyMDMwNTE5NjUwODIzNzUyMDg5MDAwMDAwMDAwMDAwMDAw
MDAwMDA5NzAwODc1U1NQU1CgLAYFYEwBAwKgIwQhVklDVE9SIEFORFJFIEZJR1VFSVJBIERFIE9M
SVZFSVJBoBkGBWBMAQMDoBAEDjE3NDY3NTE1MDAwMTA3oBcGBWBMAQMHoA4EDDAwMDAwMDAwMDAw
MIEjY2xhdWRlbmljZW1vbnRlaXJvQDNjb3JhY29lcy5jb20uYnIwCQYDVR0TBAIwADAfBgNVHSME
GDAWgBQukerWbeWyWYLcOIUpdjQWVjzQPjAOBgNVHQ8BAf8EBAMCBeAwfwYDVR0gBHgwdjB0BgZg
TAECAQwwajBoBggrBgEFBQcCARZcaHR0cDovL2ljcC1icmFzaWwuY2VydGlzaWduLmNvbS5ici9y
ZXBvc2l0b3Jpby9kcGMvQUNfQ2VydGlzaWduX1JGQi9EUENfQUNfQ2VydGlzaWduX1JGQi5wZGYw
ggEWBgNVHR8EggENMIIBCTBXoFWgU4ZRaHR0cDovL2ljcC1icmFzaWwuY2VydGlzaWduLmNvbS5i
ci9yZXBvc2l0b3Jpby9sY3IvQUNDZXJ0aXNpZ25SRkJHNC9MYXRlc3RDUkwuY3JsMFagVKBShlBo
dHRwOi8vaWNwLWJyYXNpbC5vdXRyYWxjci5jb20uYnIvcmVwb3NpdG9yaW8vbGNyL0FDQ2VydGlz
aWduUkZCRzQvTGF0ZXN0Q1JMLmNybDBWoFSgUoZQaHR0cDovL3JlcG9zaXRvcmlvLmljcGJyYXNp
bC5nb3YuYnIvbGNyL0NlcnRpc2lnbi9BQ0NlcnRpc2lnblJGQkc0L0xhdGVzdENSTC5jcmwwHQYD
VR0lBBYwFAYIKwYBBQUHAwIGCCsGAQUFBwMEMIGbBggrBgEFBQcBAQSBjjCBizBfBggrBgEFBQcw
AoZTaHR0cDovL2ljcC1icmFzaWwuY2VydGlzaWduLmNvbS5ici9yZXBvc2l0b3Jpby9jZXJ0aWZp
Y2Fkb3MvQUNfQ2VydGlzaWduX1JGQl9HNC5wN2MwKAYIKwYBBQUHMAGGHGh0dHA6Ly9vY3NwLmNl
cnRpc2lnbi5jb20uYnIwDQYJKoZIhvcNAQELBQADggIBAK6jg1WgtshmZzFTk1YUCvbxfqz+BH0L
gBmsIbeoq9xFZiPxC9f8D6EUtOIhzcWukSUJ876zLAYgGFp/JU9n/0DjK92LTxlXK5tBBY0siexF
VzoRcnFSW2kTLRGAsW7Q4dZaE3f5kta5XR2+hnTIQIiLiUo0zi3vTLQJmOAzpmEH4omTxXk2DLYO
umdkyBsPj6Fb/uu5N0r/CZ4dCNQNCEBbTwKjNst/WbrWyKt+8RugxiGMzUUQ7y7DFfYbwvpCI/OX
uP0jegX2gckFD0C4FU5rRvEsPBrw5NsrzYdXPuKYS/8BJXbIMavZSmv2jm2YIQmzequAtCtl1MmC
Hyp4yzpHFv1/OybQUx3UXeFap1m+X49BsDHGtvTv+YkHyoVIqVi2qLFLjAipy5c7lxbS7UQfqfPP
YF5PJAK1qOzGlexFHpNtBlgfBJMxu4Q73sr13nWAY7XYgWaz1ZMFNEuwEQj2sVP+u+Epix8pf9/U
OwD5PeEDIO55xcyeTbud2p5uazhXW4qWVWgaX1TY/YH2+y9lBU0JOfMX3LfYFOlGVyxdZMgaz/tg
QXp3XqlkYgeHCcaDXHdFK98lRZRl/WQuA3loQkq2+Se+t6Q8BG/lyf7xo3PrYv6MKWKlAfNyu2hX
qWC6Fs4i2tRrhf552xel2HXM5EK4e5yG73pcvHwcSUzt</X509Certificate></X509Data></KeyInfo></Signature></NFe><protNFe versao="3.10" xmlns="http://www.portalfiscal.inf.br/nfe"><infProt><tpAmb>1</tpAmb><verAplic>SVRS201701180850</verAplic><chNFe>33170117467515003386550000004480071383084614</chNFe><dhRecbto>2017-01-23T12:36:56-02:00</dhRecbto><nProt>333170009727089</nProt><digVal>q1Q7R+aTObSsjY699QnzpskmsiI=</digVal><cStat>100</cStat><xMotivo>Autorizado o uso da NF-e</xMotivo></infProt></protNFe></nfeProc>
